virtual_term/__init__.py
virtual_term/types.py
virtual_term/virtual_term.py
virtual_term-2.0.2.dist-info/METADATA
virtual_term-2.0.2.dist-info/WHEEL
virtual_term-2.0.2.dist-info/licenses/LICENSE
virtual_term-2.0.2.dist-info/RECORD
