Metadata-Version: 2.4
Name: virtual-term
Version: 2.0.2
Summary: A simple Python library for creating and interacting with virtual terminals
Project-URL: Homepage, https://github.com/MatthewScholefield/virtual-term
Author-email: "Matthew D. Scholefield" <matthew331199@gmail.com>
License: MIT
License-File: LICENSE
Classifier: Development Status :: 3 - Alpha
Classifier: Intended Audience :: Developers
Classifier: Programming Language :: Python :: 3
Classifier: Programming Language :: Python :: 3.10
Classifier: Programming Language :: Python :: 3.11
Classifier: Programming Language :: Python :: 3.12
Requires-Python: >=3.10
Requires-Dist: asyncinotify>=4.2.0
